{
    "code": 1,
    "res": [
        {
            "id": "129363",
            "outletPic": "//img01.miyabaobei.com/d1/p4/2016/11/14/1d/99/1d99e0bf2628162fcf868b19eb50d512140717827.jpg",
            "outletsItems": [
                {
                    "id": "1311463",
                    "itemPic": "http://img04.miyabaobei.com/d1/p3/item/13/1311/1311463_normal_4.jpg",
                    "name": "磁力片积木百变提拉建构塑料哒哒搭磁性玩具 186件套-v8806-9",
                    "sale_price": "399",
                    "market_price": "1299"
                },
                {
                    "id": "1310944",
                    "itemPic": "http://img04.miyabaobei.com/d1/p3/item/13/1310/1310944_normal_4.jpg",
                    "name": "益智拼搭积木智力趣味赛车塑料拼插回力车 活力橙",
                    "sale_price": "49",
                    "market_price": "98"
                },
                {
                    "id": "1311459",
                    "itemPic": "http://img04.miyabaobei.com/d1/p3/item/13/1311/1311459_normal_4.jpg",
                    "name": "磁力片积木百变提拉建构塑料哒哒搭磁性玩具 66件套V8802-9",
                    "sale_price": "168",
                    "market_price": "499"
                },
                {
                    "id": "1311462",
                    "itemPic": "http://img04.miyabaobei.com/d1/p3/item/13/1311/1311462_normal_4.jpg",
                    "name": "磁力片积木百变提拉建构塑料哒哒搭磁性玩具 146件套IQ201237-9",
                    "sale_price": "358",
                    "market_price": "999"
                },
                {
                    "id": "1310943",
                    "itemPic": "http://img04.miyabaobei.com/d1/p3/item/13/1310/1310943_normal_4.jpg",
                    "name": "益智拼搭积木智力趣味赛车塑料拼插回力车 清新绿",
                    "sale_price": "49",
                    "market_price": "98"
                },
                {
                    "id": "1310945",
                    "itemPic": "http://img04.miyabaobei.com/d1/p3/item/13/1310/1310945_normal_4.jpg",
                    "name": "益智拼搭积木智力趣味赛车塑料拼插回力车 优雅白",
                    "sale_price": "49",
                    "market_price": "98"
                }
            ]
        },
        {
            "id": "130937",
            "outletPic": "//img02.miyabaobei.com/d1/p5/2016/11/17/97/f5/97f501be5060b529fea2deb934b9e40b651045718.jpg",
            "outletsItems": [
                {
                    "id": "1002438",
                    "itemPic": "http://img04.miyabaobei.com/d1/p2/item/10/1002/1002438_normal_4.jpg",
                    "name": "苹果菠萝泥4M+ 100g*2瓶",
                    "sale_price": "39",
                    "market_price": "42"
                },
                {
                    "id": "1001699",
                    "itemPic": "http://img04.miyabaobei.com/d1/p2/item/10/1001/1001699_normal_4.jpg",
                    "name": "苹果泥4M+ 100g*2瓶",
                    "sale_price": "39",
                    "market_price": "42"
                },
                {
                    "id": "1001700",
                    "itemPic": "http://img04.miyabaobei.com/d1/p2/item/10/1001/1001700_normal_4.jpg",
                    "name": "梨子泥4M+ 100g*2瓶",
                    "sale_price": "39",
                    "market_price": "42"
                },
                {
                    "id": "1002436",
                    "itemPic": "http://img04.miyabaobei.com/d1/p2/item/10/1002/1002436_normal_4.jpg",
                    "name": "苹果橙子泥4M+ 100g*2瓶",
                    "sale_price": "39",
                    "market_price": "42"
                },
                {
                    "id": "1018802",
                    "itemPic": "http://img04.miyabaobei.com/d1/p2/item/10/1018/1018802_normal_4.jpg",
                    "name": "猪肉泥4M+ 80g*2瓶",
                    "sale_price": "45",
                    "market_price": "48"
                },
                {
                    "id": "1001704",
                    "itemPic": "http://img04.miyabaobei.com/d1/p2/item/10/1001/1001704_normal_4.jpg",
                    "name": "香蕉泥4M+ 100g*2瓶",
                    "sale_price": "39",
                    "market_price": "42"
                }
            ]
        }
    ]
}